{
  "isim": "Camlı Klima Blokları",
  "slug": "camli-klima-bloklari",
  "mahalleSlug": "tunahan",
  "aciklama": "Camlı Klima Blokları, Tunahan Mahallesi'nde Eryaman 4. Etap bölgesinde yer alıyor; 7 ayrı ada üzerinde konumlanmış bloklardan oluşuyor. Bu bloklar hakkında detaylı bilgi almak veya güncel ilanlarımızı görmek için bizimle iletişime geçebilirsiniz.",
  "adalar": [
    {
      "no": "17621",
      "etap": "4"
    },
    {
      "no": "17622",
      "etap": "4"
    },
    {
      "no": "17623",
      "etap": "4"
    },
    {
      "no": "17629",
      "etap": "4"
    },
    {
      "no": "17630",
      "etap": "4"
    },
    {
      "no": "17631",
      "etap": "4"
    },
    {
      "no": "17632",
      "etap": "4"
    }
  ]
}
